{
  "project_info": {
    "project_number": "176293790700",
    "firebase_url": "https://trafficticketbuddyclient.firebaseio.com",
    "project_id": "trafficticketbuddyclient",
    "storage_bucket": "trafficticketbuddyclient.appspot.com"
  },
  "client": [
    {
      "client_info": {
        "mobilesdk_app_id": "1:176293790700:android:88c588fd1a7eb791",
        "android_client_info": {
          "package_name": "com.trafficticketbuddy.client"
        }
      },
      "oauth_client": [
        {
          "client_id": "176293790700-j215t18tbv6e8gq0ne73sr2c6taa7fuf.apps.googleusercontent.com",
          "client_type": 3
        },
        {
          "client_id": "176293790700-j215t18tbv6e8gq0ne73sr2c6taa7fuf.apps.googleusercontent.com",
          "client_type": 3
        }
      ],
      "api_key": [
        {
          "current_key": "AIzaSyCW4HwkQpVJ_xmPGAjQTx3BCUrqW2rZZz4"
        }
      ],
      "services": {
        "analytics_service": {
          "status": 1
        },
        "appinvite_service": {
          "status": 1,
          "other_platform_oauth_client": []
        },
        "ads_service": {
          "status": 2
        }
      }
    }
  ],
  "configuration_version": "1"
}